MANIFEST.in
README.md
setup.cfg
setup.py
inid/__init__.py
inid/__main__.py
inid/city_codes.json
inid/iran_national_id.py
pyinid.egg-info/PKG-INFO
pyinid.egg-info/SOURCES.txt
pyinid.egg-info/dependency_links.txt
pyinid.egg-info/not-zip-safe
pyinid.egg-info/top_level.txt