Metadata-Version: 2.1
Name: pyinid
Version: 0.4.5
Summary: Validate And Generate Iran National ID
Home-page: https://github.com/RYNEQ/pyINID
Author: Ariyan Eghbal (RYN)
Author-email: ariyan.eghbal@gmail.com
License: GPLv2
Keywords: nid,national id,NationalID,iran,ssn,social security number
Platform: UNKNOWN
Classifier: Development Status :: 4 - Beta
Classifier: Intended Audience :: Developers
Classifier: Intended Audience :: Science/Research
Classifier: License :: OSI Approved :: GNU General Public License v2 (GPLv2)
Classifier: Programming Language :: Python :: 3.6
